setup.py
fmwrapper/__init__.py
fmwrapper/wrapper.py
fmwrapper.egg-info/PKG-INFO
fmwrapper.egg-info/SOURCES.txt
fmwrapper.egg-info/dependency_links.txt
fmwrapper.egg-info/not-zip-safe
fmwrapper.egg-info/top_level.txt