Metadata-Version: 2.1
Name: fmwrapper
Version: 0.1
Summary: Wrapper for https://facts.museum
Requires: requests
